doroutes/__init__.py
doroutes/bundles.py
doroutes/doroutes.cpython-314-x86_64-linux-gnu.so
doroutes/fanin.py
doroutes/pcells.py
doroutes/routing.py
doroutes/types.py
doroutes/util.py
doroutes-0.3.2.dist-info/METADATA
doroutes-0.3.2.dist-info/WHEEL
doroutes-0.3.2.dist-info/RECORD
doroutes-0.3.2.dist-info/licenses/LICENSE
