Metadata-Version: 2.4
Name: doroutes
Version: 0.3.2
Classifier: Development Status :: 3 - Alpha
Classifier: Intended Audience :: Science/Research
Classifier: License :: Other/Proprietary License
Classifier: Programming Language :: Python :: 3.12
Classifier: Programming Language :: Python :: 3.13
Classifier: Programming Language :: Python :: 3.14
Classifier: Programming Language :: Rust
Classifier: Topic :: Scientific/Engineering :: Physics
Classifier: Topic :: Scientific/Engineering
Requires-Dist: kfactory>=1.14.4
Requires-Dist: numpy>=2.0.0
Requires-Dist: shapely>=2.0.0
Requires-Dist: black>=25.12.0 ; extra == 'dev'
Requires-Dist: build>=1.3.0 ; extra == 'dev'
Requires-Dist: cspdk>=1.4.1 ; extra == 'dev'
Requires-Dist: gdsfactory>=9.29.1 ; extra == 'dev'
Requires-Dist: ipykernel>=7.1.0 ; extra == 'dev'
Requires-Dist: ipympl>=0.9.8 ; extra == 'dev'
Requires-Dist: jupyterlab-myst>=2.6.0 ; extra == 'dev'
Requires-Dist: maturin>=1.11.2,<2.0 ; extra == 'dev'
Requires-Dist: mkinit>=1.2.0 ; extra == 'dev'
Requires-Dist: nb-clean>=4.0.1 ; extra == 'dev'
Requires-Dist: nbstripout>=0.8.2 ; extra == 'dev'
Requires-Dist: pre-commit>=4.5.1 ; extra == 'dev'
Requires-Dist: pyright>=1.1.407 ; extra == 'dev'
Requires-Dist: pytest>=9.0.2 ; extra == 'dev'
Requires-Dist: ruff>=0.14.10 ; extra == 'dev'
Requires-Dist: tbump>=6.11.0 ; extra == 'dev'
Requires-Dist: tqdm>=4.67.1 ; extra == 'dev'
Requires-Dist: twine>=6.2.0 ; extra == 'dev'
Requires-Dist: griffe>=1.15.0 ; extra == 'docs'
Requires-Dist: mkautodoc>=0.2.0 ; extra == 'docs'
Requires-Dist: mkdocs-autorefs>=1.4.3 ; extra == 'docs'
Requires-Dist: mkdocs-material>=9.7.1 ; extra == 'docs'
Requires-Dist: mkdocs>=1.6.1 ; extra == 'docs'
Requires-Dist: mkdocstrings[python]>=1.0.0 ; extra == 'docs'
Requires-Dist: nbconvert>=7.16.6 ; extra == 'docs'
Requires-Dist: papermill>=2.6.0 ; extra == 'docs'
Provides-Extra: dev
Provides-Extra: docs
License-File: LICENSE
Summary: Advanced Routing for GDSFactory
Author-email: Floris Laporte <floris.laporte@gmail.com>
Requires-Python: >=3.12.0
